enhanced_chinese_translator/__init__.py
enhanced_chinese_translator/translator.py
enhanced_chinese_translator-1.0.1.dist-info/licenses/LICENSE
enhanced_chinese_translator-1.0.1.dist-info/METADATA
enhanced_chinese_translator-1.0.1.dist-info/WHEEL
enhanced_chinese_translator-1.0.1.dist-info/entry_points.txt
enhanced_chinese_translator-1.0.1.dist-info/top_level.txt
enhanced_chinese_translator-1.0.1.dist-info/RECORD
