Metadata-Version: 2.4
Name: enhanced-chinese-translator
Version: 1.0.1
Summary: High-performance Chinese to English translation tool with multi-threading and batch processing
Home-page: https://github.com/jasonlau233/enhanced_chinese_translator
Author: Enhanced Chinese Translator Team
Author-email: Enhanced Chinese Translator Team <support@enhanced-translator.com>
License: MIT
Project-URL: Homepage, https://github.com/jasonlau233/enhanced_chinese_translator
Project-URL: Bug Reports, https://github.com/jasonlau233/enhanced_chinese_translator/issues
Project-URL: Source, https://github.com/jasonlau233/enhanced_chinese_translator
Project-URL: Documentation, https://github.com/jasonlau233/enhanced_chinese_translator/wiki
Keywords: chinese,translation,english,batch,multi-threading,concurrent,api,google,baidu
Classifier: Development Status :: 5 - Production/Stable
Classifier: Intended Audience :: Developers
Classifier: License :: OSI Approved :: MIT License
Classifier: Operating System :: OS Independent
Classifier: Programming Language :: Python :: 3
Classifier: Programming Language :: Python :: 3.7
Classifier: Programming Language :: Python :: 3.8
Classifier: Programming Language :: Python :: 3.9
Classifier: Programming Language :: Python :: 3.10
Classifier: Programming Language :: Python :: 3.11
Classifier: Topic :: Software Development :: Internationalization
Classifier: Topic :: Text Processing :: Linguistic
Classifier: Topic :: Utilities
Requires-Python: >=3.7
License-File: LICENSE
Requires-Dist: requests>=2.25.0
Dynamic: author
Dynamic: home-page
Dynamic: license-file
Dynamic: requires-python
